{
  "recentFiles": [
    {
      "basename": "DDP",
      "path": "minimind/DDP.md"
    },
    {
      "basename": "minimind学习笔记",
      "path": "minimind/minimind学习笔记.md"
    },
    {
      "basename": "学习流程",
      "path": "minimind/学习流程.md"
    },
    {
      "basename": "评估",
      "path": "minimind/评估.md"
    },
    {
      "basename": "测试用",
      "path": "测试用.md"
    },
    {
      "basename": "手撕",
      "path": "手撕八股/手撕.md"
    },
    {
      "basename": "hot100",
      "path": "算法刷题/hot100.md"
    },
    {
      "basename": "agent",
      "path": "Agent/agent.md"
    },
    {
      "basename": "Infer",
      "path": "infer/Infer.md"
    },
    {
      "basename": "RAG",
      "path": "RAG/RAG.md"
    },
    {
      "basename": "Transformer",
      "path": "手撕八股/transformer手撕/Transformer.md"
    },
    {
      "basename": "理解Transformer",
      "path": "手撕八股/transformer手撕/理解Transformer.md"
    },
    {
      "basename": "practice_1",
      "path": "软件使用/practice_1.md"
    },
    {
      "basename": "我的第二篇笔记",
      "path": "软件使用/我的第二篇笔记.md"
    },
    {
      "basename": "我的第一篇笔记",
      "path": "软件使用/我的第一篇笔记.md"
    },
    {
      "basename": "MarkDown语言的学习",
      "path": "软件使用/MarkDown语言的学习.md"
    },
    {
      "basename": "笔记",
      "path": "点云笔记/笔记.md"
    },
    {
      "basename": "vit-v NET",
      "path": "手撕八股/transformer手撕/vit-v/vit-v NET.md"
    },
    {
      "basename": "动手学习大模型",
      "path": "模型微调/动手学习大模型.md"
    }
  ],
  "omittedPaths": [],
  "omittedTags": [],
  "updateOn": "file-open",
  "omitBookmarks": false
}